[
    {
        "key": "ctrl+shift+h",
        "command": "workbench.action.focusPreviousGroup",
        "when": "editorTextFocus"
    },
    {
        "key": "ctrl+shift+l",
        "command": "workbench.action.focusNextGroup",
        "when": "editorTextFocus"
    },
    {
        "key": "ctrl+h",
        "command": "workbench.action.previousEditor",
        "when": "editorTextFocus"
    },
    {
        "key": "ctrl+l",
        "command": "workbench.action.nextEditor",
        "when": "editorTextFocus"
    },
    {
        "key": "shift+space",
        "command": "workbench.action.quickOpen"
    },
    {
        "key": "ctrl+p",
        "command": "-workbench.action.quickOpen"
    },
    {
        "key": "ctrl+v ctrl+s",
        "command": "workbench.action.splitEditor"
    },
    {
        "key": "ctrl+\\",
        "command": "-workbench.action.splitEditor"
    },
    {
        "key": "ctrl+shift+f",
        "command": "-workbench.action.findInFiles"
    },
    {
        "key": "ctrl+shift+f",
        "command": "workbench.action.terminal.focusFind",
        "when": "terminalFindFocused && terminalProcessSupported || terminalFocus && terminalProcessSupported"
    },
    {
        "key": "ctrl+f",
        "command": "-workbench.action.terminal.focusFind",
        "when": "terminalFindFocused && terminalProcessSupported || terminalFocus && terminalProcessSupported"
    },
    {
        "key": "alt+z shift+alt",
        "command": "editor.action.triggerParameterHints",
        "when": "editorHasSignatureHelpProvider && editorTextFocus"
    },
    {
        "key": "ctrl+shift+space",
        "command": "-editor.action.triggerParameterHints",
        "when": "editorHasSignatureHelpProvider && editorTextFocus"
    },
    {
        "key": "ctrl+shift+space",
        "command": "workbench.action.terminal.toggleTerminal",
        "when": "terminal.active"
    },
    {
        "key": "ctrl+`",
        "command": "-workbench.action.terminal.toggleTerminal",
        "when": "terminal.active"
    }
]
